static_class_property/__init__.py
static_class_property-0.0.1.dist-info/LICENSE
static_class_property-0.0.1.dist-info/METADATA
static_class_property-0.0.1.dist-info/WHEEL
static_class_property-0.0.1.dist-info/top_level.txt
static_class_property-0.0.1.dist-info/RECORD
