Metadata-Version: 2.1
Name: static-class-property
Version: 0.0.1
Summary: Static Class Property
Home-page: https://github.com/maximz/static-class-property
Author: Maxim Zaslavsky
Author-email: maxim@maximz.com
License: MIT license
Classifier: Development Status :: 2 - Pre-Alpha
Classifier: Intended Audience :: Developers
Classifier: License :: OSI Approved :: MIT License
Classifier: Natural Language :: English
Classifier: Programming Language :: Python :: 3
Classifier: Programming Language :: Python :: 3.8
Classifier: Programming Language :: Python :: 3.9
Requires-Python: >=3.8
License-File: LICENSE
